sphinx_tomyst/__init__.py
sphinx_tomyst/builders/__init__.py
sphinx_tomyst/builders/myst.py
sphinx_tomyst/transform/__init__.py
sphinx_tomyst/writers/__init__.py
sphinx_tomyst/writers/accumulators.py
sphinx_tomyst/writers/markdown.py
sphinx_tomyst/writers/myst.py
sphinx_tomyst/writers/sphinxcontrib_bibtex.py
sphinx_tomyst/writers/translator.py
sphinx_tomyst/writers/writer.py
sphinx_tomyst-0.1.0a0.dist-info/LICENSE
sphinx_tomyst-0.1.0a0.dist-info/METADATA
sphinx_tomyst-0.1.0a0.dist-info/WHEEL
sphinx_tomyst-0.1.0a0.dist-info/top_level.txt
sphinx_tomyst-0.1.0a0.dist-info/RECORD
