Metadata-Version: 2.1
Name: sphinx-tomyst
Version: 0.1.0a0
Summary: Sphinx "MyST" extension: Convert your RST files into MyST documents.
Home-page: https://github.com/mmcky/sphinx-tomyst
Author: QuantEcon
Author-email: admin@quantecon.org
License: BSD
Download-URL: https://github.com/mmcky/sphinx-tomyst/archive/v0.1.0a.tar.gz
Platform: any
Classifier: Development Status :: 4 - Beta
Classifier: Framework :: Sphinx
Classifier: Operating System :: OS Independent
Classifier: Programming Language :: Python :: 3
Classifier: Framework :: Sphinx :: Extension
Requires-Dist: docutils
Requires-Dist: sphinx
Provides-Extra: code_style
Requires-Dist: flake8 (<3.8.0,>=3.7.0) ; extra == 'code_style'
Requires-Dist: black ; extra == 'code_style'
Requires-Dist: pre-commit (==1.17.0) ; extra == 'code_style'
Provides-Extra: testing
Requires-Dist: coverage ; extra == 'testing'
Requires-Dist: pytest (<4,>=3.6) ; extra == 'testing'
Requires-Dist: pytest-cov ; extra == 'testing'
Requires-Dist: pytest-regressions ; extra == 'testing'
Requires-Dist: sphinxcontrib-bibtex (~=1.0) ; extra == 'testing'
